{"user_id":"76561198049919646","rank":9,"name":"Idling to Rule the Gods"}
{"user_id":"76561198049919646","rank":9,"name":"Idling to Rule the Gods"}
{"user_id":"76561198049919646","rank":10,"name":"Battleborn"}
{"user_id":"76561198049919646","rank":10,"name":"Battleborn"}
{"user_id":"76561198050138573","rank":1,"name":"Resident Evil™ 5/ Biohazard 5®"}
{"user_id":"76561198050138573","rank":2,"name":"Grand Theft Auto V"}
{"user_id":"76561198050138573","rank":3,"name":"Crusaders of the Lost Idols"}
{"user_id":"76561198050138573","rank":3,"name":"Crusaders of the Lost Idols"}
{"user_id":"76561198050138573","rank":4,"name":"Left 4 Dead 2"}
{"user_id":"76561198050138573","rank":5,"name":"Trove"}
{"user_id":"76561198050138573","rank":6,"name":"No More Room in Hell"}
{"user_id":"76561198050138573","rank":7,"name":"Clicker Heroes"}
{"user_id":"76561198050138573","rank":7,"name":"Clicker Heroes"}
{"user_id":"76561198050138573","rank":8,"name":"F1 2012™"}
{"user_id":"76561198050138573","rank":9,"name":"Shonen Idle Z"}
{"user_id":"76561198050138573","rank":9,"name":"Shonen Idle Z"}
{"user_id":"76561198050138573","rank":10,"name":"Tap Adventure: Time Travel"}
{"user_id":"76561198050973513","rank":1,"name":"Counter-Strike: Global Offensive"}
{"user_id":"76561198050973513","rank":2,"name":"Killing Floor 2"}
{"user_id":"76561198050973513","rank":3,"name":"Tom Clancy's Rainbow Six® Siege"}
{"user_id":"76561198050973513","rank":3,"name":"Tom Clancy's Rainbow Six® Siege"}
{"user_id":"76561198050973513","rank":3,"name":"Tom Clancy's Rainbow Six® Siege"}
{"user_id":"76561198050973513","rank":3,"name":"Tom Clancy's Rainbow Six® Siege"}
{"user_id":"76561198050973513","rank":3,"name":"Tom Clancy's Rainbow Six® Siege"}
{"user_id":"76561198050973513","rank":3,"name":"Tom Clancy's Rainbow Six® Siege"}
{"user_id":"76561198050973513","rank":3,"name":"Tom Clancy's Rainbow Six® Siege"}
{"user_id":"76561198050973513","rank":3,"name":"Tom Clancy's Rainbow Six® Siege"}
{"user_id":"76561198050973513","rank":3,"name":"Tom Clancy's Rainbow Six® Siege"}
{"user_id":"76561198050973513","rank":3,"name":"Tom Clancy's Rainbow Six® Siege"}
